PyColored/__init__.py
PyColored/colours.py
PyColored-1.0.2.dist-info/LICENSE
PyColored-1.0.2.dist-info/METADATA
PyColored-1.0.2.dist-info/WHEEL
PyColored-1.0.2.dist-info/top_level.txt
PyColored-1.0.2.dist-info/RECORD
